gradio_huggingfacehub_search/__init__.py
gradio_huggingfacehub_search/huggingfacehubsearch.py
gradio_huggingfacehub_search/huggingfacehubsearch.pyi
gradio_huggingfacehub_search/templates/component/index.js
gradio_huggingfacehub_search/templates/component/style.css
gradio_huggingfacehub_search/templates/example/index.js
gradio_huggingfacehub_search/templates/example/style.css
gradio_huggingfacehub_search-0.0.12.dist-info/METADATA
gradio_huggingfacehub_search-0.0.12.dist-info/WHEEL
gradio_huggingfacehub_search-0.0.12.dist-info/RECORD
