Metadata-Version: 2.3
Name: gradio_huggingfacehub_search
Version: 0.0.12
Summary: Gradio component for searching Hugging Face Hub models, datasets, Spaces, and more
Project-URL: repository, https://github.com/radames/gradio_huggingfacehub_search
Project-URL: space, https://huggingface.co/spaces/radames/gradio_huggingfacehub_search
Author-email: Radamés Ajna <radamajna@gmail.com>
License: MIT
Keywords: gradio-custom-component,hub,huggingface,search
Classifier: Development Status :: 3 - Alpha
Classifier: Operating System :: OS Independent
Classifier: Programming Language :: Python :: 3
Classifier: Programming Language :: Python :: 3 :: Only
Classifier: Programming Language :: Python :: 3.8
Classifier: Programming Language :: Python :: 3.9
Classifier: Programming Language :: Python :: 3.10
Classifier: Programming Language :: Python :: 3.11
Classifier: Topic :: Scientific/Engineering
Classifier: Topic :: Scientific/Engineering :: Artificial Intelligence
Classifier: Topic :: Scientific/Engineering :: Visualization
Requires-Python: >=3.10
Requires-Dist: gradio<6.0,>=4.0
Provides-Extra: dev
Requires-Dist: build; extra == 'dev'
Requires-Dist: twine; extra == 'dev'
